setup.py
luv2see/__init__.py
luv2see/targetingSystem.py
luv2see.egg-info/PKG-INFO
luv2see.egg-info/SOURCES.txt
luv2see.egg-info/dependency_links.txt
luv2see.egg-info/not-zip-safe
luv2see.egg-info/top_level.txt