Metadata-Version: 1.0
Name: luv2see
Version: 0.1
Summary: Rapid Acceleration Team 4593 Vision Library
Home-page: https://github.com/Rapid-Acceleration-4593
Author: Rapid Acceleration Team
Author-email: julian.brackins@mines.sdsmt.edu
License: None
Platform: UNKNOWN
